pyfldm/__init__.py
pyfldm/appmonitor.py
pyfldm/client.py
pyfldm/submodules/__init__.py
pyfldm/submodules/base_call.py
pyfldm/submodules/flconfig_manager.py
pyfldm/submodules/fldigi.py
pyfldm/submodules/ioconfig.py
pyfldm/submodules/log.py
pyfldm/submodules/main.py
pyfldm/submodules/modem.py
pyfldm/submodules/navtex.py
pyfldm/submodules/rig.py
pyfldm/submodules/spot.py
pyfldm/submodules/text.py
pyfldm/submodules/wefax.py
pyfldm-1.0.1.dist-info/LICENSE
pyfldm-1.0.1.dist-info/METADATA
pyfldm-1.0.1.dist-info/WHEEL
pyfldm-1.0.1.dist-info/top_level.txt
pyfldm-1.0.1.dist-info/RECORD
