Metadata-Version: 2.1
Name: pyfldm
Version: 1.0.1
Summary: A library for controlling Fldigi via xmlrpc
Author-email: Phillip Hall <phall131@pm.me>
Project-URL: Homepage, https://github.com/philliphall131/pyfldm
Classifier: Programming Language :: Python :: 3
Classifier: License :: OSI Approved :: GNU Lesser General Public License v2 or later (LGPLv2+)
Classifier: Operating System :: OS Independent
Requires-Python: >=3.8
License-File: LICENSE
Requires-Dist: psutil >=5.9.5
Requires-Dist: xvfbwrapper >=0.2.9 ; platform_system == "Linux"
